pyfilehandlers/__init__.py
pyfilehandlers/file_dat.py
pyfilehandlers/file_extension.py
pyfilehandlers/file_handler.py
pyfilehandlers/file_json.py
pyfilehandlers/file_minecraft_dat.py
pyfilehandlers/file_txt.py
pyfilehandlers/file_yaml.py
pyfilehandlers-1.1.1.dist-info/METADATA
pyfilehandlers-1.1.1.dist-info/WHEEL
pyfilehandlers-1.1.1.dist-info/licenses/LICENSE
pyfilehandlers-1.1.1.dist-info/RECORD
